__init__.py
mpPy6/CBase.py
mpPy6/CCommandRecord.py
mpPy6/CException.py
mpPy6/CProcess.py
mpPy6/CProcessControl.py
mpPy6/CProperty.py
mpPy6/CResultRecord.py
mpPy6/__init__.py
mpPy6/testings.py
mpPy6-6.0.0.dist-info/LICENSE
mpPy6-6.0.0.dist-info/METADATA
mpPy6-6.0.0.dist-info/WHEEL
mpPy6-6.0.0.dist-info/top_level.txt
mpPy6-6.0.0.dist-info/RECORD
