Metadata-Version: 2.1
Name: mpPy6
Version: 6.0.0
Summary: A Pyside-to-Process Control class to facilitate communication between multiple processes while utilizing PySide6 for graphical user interfaces (GUIs). This module aims to provide a seamless solution for building applications with parallel processing capabilities and interactive UI components.
Author-email: Christoph Schmidt <cschmidt.fs@gmail.com>
Project-URL: Homepage, https://github.com/agentsmith29/mpPy6
Classifier: Programming Language :: Python :: 3
Classifier: License :: OSI Approved :: GNU General Public License v3 (GPLv3)
Classifier: Operating System :: OS Independent
Requires-Python: >=3.7
License-File: LICENSE
Requires-Dist: PySide6
Requires-Dist: rich
